xcomcan/__init__.py
xcomcan/addresses.py
xcomcan/client.py
xcomcan/node.py
xcomcan-0.9.1.dist-info/LICENSE
xcomcan-0.9.1.dist-info/METADATA
xcomcan-0.9.1.dist-info/WHEEL
xcomcan-0.9.1.dist-info/top_level.txt
xcomcan-0.9.1.dist-info/RECORD
