Metadata-Version: 2.1
Name: xcomcan
Version: 0.9.1
Summary: Package that let easily interact with the Xcom-CAN device
Home-page: https://github.com/studer-innotec/xcomcan
Author: Studer Innotec SA
Author-email: develop@studer-innotec.com
Maintainer-email: develop@studer-innotec.com
License: MIT
Project-URL: Documentation, https://xcomcan.readthedocs.io/en/latest/index.html
Project-URL: Issues tracker, https://github.com/studer-innotec/xcomcan/issues
Project-URL: Source Code, https://github.com/studer-innotec/xcomcan
Platform: UNKNOWN
Classifier: Programming Language :: Python :: 3
Classifier: License :: OSI Approved :: MIT License
Classifier: Operating System :: OS Independent
Classifier: Development Status :: 4 - Beta
Classifier: Topic :: Communications
Classifier: Topic :: Software Development :: Libraries
Classifier: Topic :: Software Development :: Libraries :: Python Modules
Requires-Python: >=3.6.8
Requires-Dist: stucancommon (>=0.9.1)
